{".class": "MypyFile", "_fullname": "liquid.environment", "future_import_flags": ["annotations"], "is_partial_stub_package": false, "is_stub": false, "names": {".class": "SymbolTable", "Any": {".class": "SymbolTableNode", "cross_ref": "typing.Any", "kind": "Gdef"}, "BooleanExpression": {".class": "SymbolTableNode", "cross_ref": "liquid.expression.BooleanExpression", "kind": "Gdef"}, "BoundTemplate": {".class": "SymbolTableNode", "cross_ref": "liquid.template.BoundTemplate", "kind": "Gdef"}, "Callable": {".class": "SymbolTableNode", "cross_ref": "typing.Callable", "kind": "Gdef"}, "ClassVar": {".class": "SymbolTableNode", "cross_ref": "typing.ClassVar", "kind": "Gdef"}, "Context": {".class": "SymbolTableNode", "cross_ref": "liquid.context.Context", "kind": "Gdef"}, "Dict": {".class": "SymbolTableNode", "cross_ref": "typing.Dict", "kind": "Gdef"}, "Environment": {".class": "SymbolTableNode", "kind": "Gdef", "node": {".class": "TypeInfo", "_promote": [], "abstract_attributes": [], "bases": ["builtins.object"], "declared_metaclass": null, "defn": {".class": "ClassDef", "fullname": "liquid.environment.Environment", "name": "Environment", "type_vars": []}, "deletable_attributes": [], "flags": [], "fullname": "liquid.environment.Environment", "has_param_spec_type": false, "metaclass_type": null, "metadata": {}, "module_name": "liquid.environment", "mro": ["liquid.environment.Environment", "builtins.object"], "names": {".class": "SymbolTable", "__hash__": {".class": "SymbolTableNode", "kind": "Mdef", "node": {".class": "FuncDef", "arg_kinds": [0], "arg_names": ["self"], "flags": [], "fullname": "liquid.environment.Environment.__hash__", "name": "__hash__", "type": {".class": "CallableType", "arg_kinds": [0], "arg_names": ["self"], "arg_types": ["liquid.environment.Environment"], "bound_args": [], "def_extras": {"first_arg": "self"}, "fallback": "builtins.function", "from_concatenate": false, "implicit": false, "is_ellipsis_args": false, "name": "__hash__ of Environment", "ret_type": "builtins.int", "type_guard": null, "variables": []}}}, "__init__": {".class": "SymbolTableNode", "kind": "Mdef", "node": {".class": "FuncDef", "arg_kinds": [0, 1, 1, 1, 1, 1, 1, 1, 1, 1, 1, 1, 1, 1, 1, 1, 1, 1], "arg_names": ["self", "tag_start_string", "tag_end_string", "statement_start_string", "statement_end_string", "strip_tags", "tolerance", "loader", "undefined", "strict_filters", "autoescape", "auto_reload", "cache_size", "globals", "template_comments", "comment_start_string", "comment_end_string", "expression_cache_size"], "flags": [], "fullname": "liquid.environment.Environment.__init__", "name": "__init__", "type": {".class": "CallableType", "arg_kinds": [0, 1, 1, 1, 1, 1, 1, 1, 1, 1, 1, 1, 1, 1, 1, 1, 1, 1], "arg_names": ["self", "tag_start_string", "tag_end_string", "statement_start_string", "statement_end_string", "strip_tags", "tolerance", "loader", "undefined", "strict_filters", "autoescape", "auto_reload", "cache_size", "globals", "template_comments", "comment_start_string", "comment_end_string", "expression_cache_size"], "arg_types": ["liquid.environment.Environment", "builtins.str", "builtins.str", "builtins.str", "builtins.str", "builtins.bool", "liquid.mode.Mode", {".class": "UnionType", "items": ["liquid.loaders.BaseLoader", {".class": "NoneType"}]}, {".class": "TypeType", "item": "liquid.context.Undefined"}, "builtins.bool", "builtins.bool", "builtins.bool", "builtins.int", {".class": "UnionType", "items": [{".class": "Instance", "args": ["builtins.str", "builtins.object"], "type_ref": "typing.Mapping"}, {".class": "NoneType"}]}, "builtins.bool", "builtins.str", "builtins.str", "builtins.int"], "bound_args": [], "def_extras": {"first_arg": "self"}, "fallback": "builtins.function", "from_concatenate": false, "implicit": false, "is_ellipsis_args": false, "name": "__init__ of Environment", "ret_type": {".class": "NoneType"}, "type_guard": null, "variables": []}}}, "_check_cache": {".class": "SymbolTableNode", "kind": "Mdef", "node": {".class": "FuncDef", "arg_kinds": [0, 0, 1], "arg_names": ["self", "name", "globals"], "flags": [], "fullname": "liquid.environment.Environment._check_cache", "name": "_check_cache", "type": {".class": "CallableType", "arg_kinds": [0, 0, 1], "arg_names": ["self", "name", "globals"], "arg_types": ["liquid.environment.Environment", "builtins.str", {".class": "UnionType", "items": [{".class": "Instance", "args": ["builtins.str", "builtins.object"], "type_ref": "typing.Mapping"}, {".class": "NoneType"}]}], "bound_args": [], "def_extras": {"first_arg": "self"}, "fallback": "builtins.function", "from_concatenate": false, "implicit": false, "is_ellipsis_args": false, "name": "_check_cache of Environment", "ret_type": {".class": "UnionType", "items": ["liquid.template.BoundTemplate", {".class": "NoneType"}]}, "type_guard": null, "variables": []}}}, "_get_expression_parsers": {".class": "SymbolTableNode", "kind": "Mdef", "node": {".class": "FuncDef", "arg_kinds": [0, 1], "arg_names": ["self", "cache_size"], "flags": [], "fullname": "liquid.environment.Environment._get_expression_parsers", "name": "_get_expression_parsers", "type": {".class": "CallableType", "arg_kinds": [0, 1], "arg_names": ["self", "cache_size"], "arg_types": ["liquid.environment.Environment", "builtins.int"], "bound_args": [], "def_extras": {"first_arg": "self"}, "fallback": "builtins.function", "from_concatenate": false, "implicit": false, "is_ellipsis_args": false, "name": "_get_expression_parsers of Environment", "ret_type": {".class": "TupleType", "implicit": false, "items": [{".class": "CallableType", "arg_kinds": [0], "arg_names": [null], "arg_types": ["builtins.str"], "bound_args": [], "def_extras": {}, "fallback": "builtins.function", "from_concatenate": false, "implicit": false, "is_ellipsis_args": false, "name": null, "ret_type": "liquid.expression.BooleanExpression", "type_guard": null, "variables": []}, {".class": "CallableType", "arg_kinds": [0], "arg_names": [null], "arg_types": ["builtins.str"], "bound_args": [], "def_extras": {}, "fallback": "builtins.function", "from_concatenate": false, "implicit": false, "is_ellipsis_args": false, "name": null, "ret_type": "liquid.expression.FilteredExpression", "type_guard": null, "variables": []}, {".class": "CallableType", "arg_kinds": [0], "arg_names": [null], "arg_types": ["builtins.str"], "bound_args": [], "def_extras": {}, "fallback": "builtins.function", "from_concatenate": false, "implicit": false, "is_ellipsis_args": false, "name": null, "ret_type": "liquid.expression.LoopExpression", "type_guard": null, "variables": []}], "partial_fallback": {".class": "Instance", "args": [{".class": "AnyType", "missing_import_name": null, "source_any": null, "type_of_any": 6}], "type_ref": "builtins.tuple"}}, "type_guard": null, "variables": []}}}, "add_filter": {".class": "SymbolTableNode", "kind": "Mdef", "node": {".class": "FuncDef", "arg_kinds": [0, 0, 0], "arg_names": ["self", "name", "func"], "flags": [], "fullname": "liquid.environment.Environment.add_filter", "name": "add_filter", "type": {".class": "CallableType", "arg_kinds": [0, 0, 0], "arg_names": ["self", "name", "func"], "arg_types": ["liquid.environment.Environment", "builtins.str", {".class": "CallableType", "arg_kinds": [2, 4], "arg_names": [null, null], "arg_types": [{".class": "AnyType", "missing_import_name": null, "source_any": null, "type_of_any": 2}, {".class": "AnyType", "missing_import_name": null, "source_any": null, "type_of_any": 2}], "bound_args": [], "def_extras": {}, "fallback": "builtins.function", "from_concatenate": false, "implicit": false, "is_ellipsis_args": true, "name": null, "ret_type": {".class": "AnyType", "missing_import_name": null, "source_any": null, "type_of_any": 2}, "type_guard": null, "variables": []}], "bound_args": [], "def_extras": {"first_arg": "self"}, "fallback": "builtins.function", "from_concatenate": false, "implicit": false, "is_ellipsis_args": false, "name": "add_filter of Environment", "ret_type": {".class": "NoneType"}, "type_guard": null, "variables": []}}}, "add_tag": {".class": "SymbolTableNode", "kind": "Mdef", "node": {".class": "FuncDef", "arg_kinds": [0, 0], "arg_names": ["self", "tag"], "flags": [], "fullname": "liquid.environment.Environment.add_tag", "name": "add_tag", "type": {".class": "CallableType", "arg_kinds": [0, 0], "arg_names": ["self", "tag"], "arg_types": ["liquid.environment.Environment", {".class": "TypeType", "item": "liquid.tag.Tag"}], "bound_args": [], "def_extras": {"first_arg": "self"}, "fallback": "builtins.function", "from_concatenate": false, "implicit": false, "is_ellipsis_args": false, "name": "add_tag of Environment", "ret_type": {".class": "NoneType"}, "type_guard": null, "variables": []}}}, "auto_reload": {".class": "SymbolTableNode", "implicit": true, "kind": "Mdef", "node": {".class": "Var", "flags": [], "fullname": "liquid.environment.Environment.auto_reload", "name": "auto_reload", "type": "builtins.bool"}}, "autoescape": {".class": "SymbolTableNode", "implicit": true, "kind": "Mdef", "node": {".class": "Var", "flags": [], "fullname": "liquid.environment.Environment.autoescape", "name": "autoescape", "type": "builtins.bool"}}, "cache": {".class": "SymbolTableNode", "implicit": true, "kind": "Mdef", "node": {".class": "Var", "flags": ["explicit_self_type", "is_ready"], "fullname": "liquid.environment.Environment.cache", "name": "cache", "type": {".class": "Instance", "args": [{".class": "AnyType", "missing_import_name": null, "source_any": null, "type_of_any": 2}, {".class": "AnyType", "missing_import_name": null, "source_any": null, "type_of_any": 2}], "type_ref": "typing.MutableMapping"}}}, "comment_end_string": {".class": "SymbolTableNode", "implicit": true, "kind": "Mdef", "node": {".class": "Var", "flags": [], "fullname": "liquid.environment.Environment.comment_end_string", "name": "comment_end_string", "type": "builtins.str"}}, "comment_start_string": {".class": "SymbolTableNode", "implicit": true, "kind": "Mdef", "node": {".class": "Var", "flags": [], "fullname": "liquid.environment.Environment.comment_start_string", "name": "comment_start_string", "type": "builtins.str"}}, "context_depth_limit": {".class": "SymbolTableNode", "kind": "Mdef", "node": {".class": "Var", "flags": ["is_initialized_in_class", "is_classvar", "is_ready", "has_explicit_value"], "fullname": "liquid.environment.Environment.context_depth_limit", "name": "context_depth_limit", "type": "builtins.int"}}, "error": {".class": "SymbolTableNode", "kind": "Mdef", "node": {".class": "FuncDef", "arg_kinds": [0, 0, 1, 1], "arg_names": ["self", "exc", "msg", "linenum"], "flags": [], "fullname": "liquid.environment.Environment.error", "name": "error", "type": {".class": "CallableType", "arg_kinds": [0, 0, 1, 1], "arg_names": ["self", "exc", "msg", "linenum"], "arg_types": ["liquid.environment.Environment", {".class": "UnionType", "items": [{".class": "TypeType", "item": "liquid.exceptions.Error"}, "liquid.exceptions.Error"]}, {".class": "UnionType", "items": ["builtins.str", {".class": "NoneType"}]}, {".class": "UnionType", "items": ["builtins.int", {".class": "NoneType"}]}], "bound_args": [], "def_extras": {"first_arg": "self"}, "fallback": "builtins.function", "from_concatenate": false, "implicit": false, "is_ellipsis_args": false, "name": "error of Environment", "ret_type": {".class": "NoneType"}, "type_guard": null, "variables": []}}}, "expression_cache_size": {".class": "SymbolTableNode", "implicit": true, "kind": "Mdef", "node": {".class": "Var", "flags": [], "fullname": "liquid.environment.Environment.expression_cache_size", "name": "expression_cache_size", "type": "builtins.int"}}, "filters": {".class": "SymbolTableNode", "implicit": true, "kind": "Mdef", "node": {".class": "Var", "flags": ["explicit_self_type", "is_ready"], "fullname": "liquid.environment.Environment.filters", "name": "filters", "type": {".class": "Instance", "args": ["builtins.str", {".class": "CallableType", "arg_kinds": [2, 4], "arg_names": [null, null], "arg_types": [{".class": "AnyType", "missing_import_name": null, "source_any": null, "type_of_any": 2}, {".class": "AnyType", "missing_import_name": null, "source_any": null, "type_of_any": 2}], "bound_args": [], "def_extras": {}, "fallback": "builtins.function", "from_concatenate": false, "implicit": false, "is_ellipsis_args": true, "name": null, "ret_type": {".class": "AnyType", "missing_import_name": null, "source_any": null, "type_of_any": 2}, "type_guard": null, "variables": []}], "type_ref": "builtins.dict"}}}, "from_string": {".class": "SymbolTableNode", "kind": "Mdef", "node": {".class": "FuncDef", "arg_kinds": [0, 0, 1, 1, 1, 1], "arg_names": ["self", "source", "name", "path", "globals", "matter"], "flags": [], "fullname": "liquid.environment.Environment.from_string", "name": "from_string", "type": {".class": "CallableType", "arg_kinds": [0, 0, 1, 1, 1, 1], "arg_names": ["self", "source", "name", "path", "globals", "matter"], "arg_types": ["liquid.environment.Environment", "builtins.str", "builtins.str", {".class": "UnionType", "items": ["builtins.str", "pathlib.Path", {".class": "NoneType"}]}, {".class": "UnionType", "items": [{".class": "Instance", "args": ["builtins.str", "builtins.object"], "type_ref": "typing.Mapping"}, {".class": "NoneType"}]}, {".class": "UnionType", "items": [{".class": "Instance", "args": ["builtins.str", "builtins.object"], "type_ref": "typing.Mapping"}, {".class": "NoneType"}]}], "bound_args": [], "def_extras": {"first_arg": "self"}, "fallback": "builtins.function", "from_concatenate": false, "implicit": false, "is_ellipsis_args": false, "name": "from_string of Environment", "ret_type": "liquid.template.BoundTemplate", "type_guard": null, "variables": []}}}, "get_template": {".class": "SymbolTableNode", "kind": "Mdef", "node": {".class": "FuncDef", "arg_kinds": [0, 0, 1], "arg_names": ["self", "name", "globals"], "flags": [], "fullname": "liquid.environment.Environment.get_template", "name": "get_template", "type": {".class": "CallableType", "arg_kinds": [0, 0, 1], "arg_names": ["self", "name", "globals"], "arg_types": ["liquid.environment.Environment", "builtins.str", {".class": "UnionType", "items": [{".class": "Instance", "args": ["builtins.str", "builtins.object"], "type_ref": "typing.Mapping"}, {".class": "NoneType"}]}], "bound_args": [], "def_extras": {"first_arg": "self"}, "fallback": "builtins.function", "from_concatenate": false, "implicit": false, "is_ellipsis_args": false, "name": "get_template of Environment", "ret_type": "liquid.template.BoundTemplate", "type_guard": null, "variables": []}}}, "get_template_async": {".class": "SymbolTableNode", "kind": "Mdef", "node": {".class": "FuncDef", "arg_kinds": [0, 0, 1], "arg_names": ["self", "name", "globals"], "flags": ["is_coroutine"], "fullname": "liquid.environment.Environment.get_template_async", "name": "get_template_async", "type": {".class": "CallableType", "arg_kinds": [0, 0, 1], "arg_names": ["self", "name", "globals"], "arg_types": ["liquid.environment.Environment", "builtins.str", {".class": "UnionType", "items": [{".class": "Instance", "args": ["builtins.str", "builtins.object"], "type_ref": "typing.Mapping"}, {".class": "NoneType"}]}], "bound_args": [], "def_extras": {"first_arg": "self"}, "fallback": "builtins.function", "from_concatenate": false, "implicit": false, "is_ellipsis_args": false, "name": "get_template_async of Environment", "ret_type": {".class": "Instance", "args": [{".class": "AnyType", "missing_import_name": null, "source_any": null, "type_of_any": 6}, {".class": "AnyType", "missing_import_name": null, "source_any": null, "type_of_any": 6}, "liquid.template.BoundTemplate"], "type_ref": "typing.Coroutine"}, "type_guard": null, "variables": []}}}, "get_template_with_context": {".class": "SymbolTableNode", "kind": "Mdef", "node": {".class": "FuncDef", "arg_kinds": [0, 0, 0, 4], "arg_names": ["self", "context", "name", "kwargs"], "flags": [], "fullname": "liquid.environment.Environment.get_template_with_context", "name": "get_template_with_context", "type": {".class": "CallableType", "arg_kinds": [0, 0, 0, 4], "arg_names": ["self", "context", "name", "kwargs"], "arg_types": ["liquid.environment.Environment", "liquid.context.Context", "builtins.str", "builtins.str"], "bound_args": [], "def_extras": {"first_arg": "self"}, "fallback": "builtins.function", "from_concatenate": false, "implicit": false, "is_ellipsis_args": false, "name": "get_template_with_context of Environment", "ret_type": "liquid.template.BoundTemplate", "type_guard": null, "variables": []}}}, "get_template_with_context_async": {".class": "SymbolTableNode", "kind": "Mdef", "node": {".class": "FuncDef", "arg_kinds": [0, 0, 0, 4], "arg_names": ["self", "context", "name", "kwargs"], "flags": ["is_coroutine"], "fullname": "liquid.environment.Environment.get_template_with_context_async", "name": "get_template_with_context_async", "type": {".class": "CallableType", "arg_kinds": [0, 0, 0, 4], "arg_names": ["self", "context", "name", "kwargs"], "arg_types": ["liquid.environment.Environment", "liquid.context.Context", "builtins.str", "builtins.str"], "bound_args": [], "def_extras": {"first_arg": "self"}, "fallback": "builtins.function", "from_concatenate": false, "implicit": false, "is_ellipsis_args": false, "name": "get_template_with_context_async of Environment", "ret_type": {".class": "Instance", "args": [{".class": "AnyType", "missing_import_name": null, "source_any": null, "type_of_any": 6}, {".class": "AnyType", "missing_import_name": null, "source_any": null, "type_of_any": 6}, "liquid.template.BoundTemplate"], "type_ref": "typing.Coroutine"}, "type_guard": null, "variables": []}}}, "globals": {".class": "SymbolTableNode", "implicit": true, "kind": "Mdef", "node": {".class": "Var", "flags": ["explicit_self_type", "is_ready"], "fullname": "liquid.environment.Environment.globals", "name": "globals", "type": {".class": "Instance", "args": ["builtins.str", "builtins.object"], "type_ref": "typing.Mapping"}}}, "loader": {".class": "SymbolTableNode", "implicit": true, "kind": "Mdef", "node": {".class": "Var", "flags": [], "fullname": "liquid.environment.Environment.loader", "name": "loader", "type": "liquid.loaders.BaseLoader"}}, "local_namespace_limit": {".class": "SymbolTableNode", "kind": "Mdef", "node": {".class": "Var", "flags": ["is_initialized_in_class", "is_classvar", "is_ready", "has_explicit_value"], "fullname": "liquid.environment.Environment.local_namespace_limit", "name": "local_namespace_limit", "type": {".class": "UnionType", "items": ["builtins.int", {".class": "NoneType"}]}}}, "loop_iteration_limit": {".class": "SymbolTableNode", "kind": "Mdef", "node": {".class": "Var", "flags": ["is_initialized_in_class", "is_classvar", "is_ready", "has_explicit_value"], "fullname": "liquid.environment.Environment.loop_iteration_limit", "name": "loop_iteration_limit", "type": {".class": "UnionType", "items": ["builtins.int", {".class": "NoneType"}]}}}, "make_globals": {".class": "SymbolTableNode", "kind": "Mdef", "node": {".class": "FuncDef", "arg_kinds": [0, 1], "arg_names": ["self", "globals"], "flags": [], "fullname": "liquid.environment.Environment.make_globals", "name": "make_globals", "type": {".class": "CallableType", "arg_kinds": [0, 1], "arg_names": ["self", "globals"], "arg_types": ["liquid.environment.Environment", {".class": "UnionType", "items": [{".class": "Instance", "args": ["builtins.str", "builtins.object"], "type_ref": "typing.Mapping"}, {".class": "NoneType"}]}], "bound_args": [], "def_extras": {"first_arg": "self"}, "fallback": "builtins.function", "from_concatenate": false, "implicit": false, "is_ellipsis_args": false, "name": "make_globals of Environment", "ret_type": {".class": "Instance", "args": ["builtins.str", "builtins.object"], "type_ref": "builtins.dict"}, "type_guard": null, "variables": []}}}, "mode": {".class": "SymbolTableNode", "implicit": true, "kind": "Mdef", "node": {".class": "Var", "flags": [], "fullname": "liquid.environment.Environment.mode", "name": "mode", "type": "liquid.mode.Mode"}}, "output_stream_limit": {".class": "SymbolTableNode", "kind": "Mdef", "node": {".class": "Var", "flags": ["is_initialized_in_class", "is_classvar", "is_ready", "has_explicit_value"], "fullname": "liquid.environment.Environment.output_stream_limit", "name": "output_stream_limit", "type": {".class": "UnionType", "items": ["builtins.int", {".class": "NoneType"}]}}}, "parse": {".class": "SymbolTableNode", "kind": "Mdef", "node": {".class": "FuncDef", "arg_kinds": [0, 0], "arg_names": ["self", "source"], "flags": [], "fullname": "liquid.environment.Environment.parse", "name": "parse", "type": {".class": "CallableType", "arg_kinds": [0, 0], "arg_names": ["self", "source"], "arg_types": ["liquid.environment.Environment", "builtins.str"], "bound_args": [], "def_extras": {"first_arg": "self"}, "fallback": "builtins.function", "from_concatenate": false, "implicit": false, "is_ellipsis_args": false, "name": "parse of Environment", "ret_type": "liquid.ast.ParseTree", "type_guard": null, "variables": []}}}, "parse_boolean_expression_value": {".class": "SymbolTableNode", "implicit": true, "kind": "Mdef", "node": {".class": "Var", "flags": [], "fullname": "liquid.environment.Environment.parse_boolean_expression_value", "name": "parse_boolean_expression_value", "type": {".class": "CallableType", "arg_kinds": [0], "arg_names": [null], "arg_types": ["builtins.str"], "bound_args": [], "def_extras": {}, "fallback": "builtins.function", "from_concatenate": false, "implicit": false, "is_ellipsis_args": false, "name": null, "ret_type": "liquid.expression.BooleanExpression", "type_guard": null, "variables": []}}}, "parse_filtered_expression_value": {".class": "SymbolTableNode", "implicit": true, "kind": "Mdef", "node": {".class": "Var", "flags": [], "fullname": "liquid.environment.Environment.parse_filtered_expression_value", "name": "parse_filtered_expression_value", "type": {".class": "CallableType", "arg_kinds": [0], "arg_names": [null], "arg_types": ["builtins.str"], "bound_args": [], "def_extras": {}, "fallback": "builtins.function", "from_concatenate": false, "implicit": false, "is_ellipsis_args": false, "name": null, "ret_type": "liquid.expression.FilteredExpression", "type_guard": null, "variables": []}}}, "parse_loop_expression_value": {".class": "SymbolTableNode", "implicit": true, "kind": "Mdef", "node": {".class": "Var", "flags": [], "fullname": "liquid.environment.Environment.parse_loop_expression_value", "name": "parse_loop_expression_value", "type": {".class": "CallableType", "arg_kinds": [0], "arg_names": [null], "arg_types": ["builtins.str"], "bound_args": [], "def_extras": {}, "fallback": "builtins.function", "from_concatenate": false, "implicit": false, "is_ellipsis_args": false, "name": null, "ret_type": "liquid.expression.LoopExpression", "type_guard": null, "variables": []}}}, "set_expression_cache_size": {".class": "SymbolTableNode", "kind": "Mdef", "node": {".class": "FuncDef", "arg_kinds": [0, 1], "arg_names": ["self", "maxsize"], "flags": [], "fullname": "liquid.environment.Environment.set_expression_cache_size", "name": "set_expression_cache_size", "type": {".class": "CallableType", "arg_kinds": [0, 1], "arg_names": ["self", "maxsize"], "arg_types": ["liquid.environment.Environment", "builtins.int"], "bound_args": [], "def_extras": {"first_arg": "self"}, "fallback": "builtins.function", "from_concatenate": false, "implicit": false, "is_ellipsis_args": false, "name": "set_expression_cache_size of Environment", "ret_type": {".class": "NoneType"}, "type_guard": null, "variables": []}}}, "statement_end_string": {".class": "SymbolTableNode", "implicit": true, "kind": "Mdef", "node": {".class": "Var", "flags": [], "fullname": "liquid.environment.Environment.statement_end_string", "name": "statement_end_string", "type": "builtins.str"}}, "statement_start_string": {".class": "SymbolTableNode", "implicit": true, "kind": "Mdef", "node": {".class": "Var", "flags": [], "fullname": "liquid.environment.Environment.statement_start_string", "name": "statement_start_string", "type": "builtins.str"}}, "strict_filters": {".class": "SymbolTableNode", "implicit": true, "kind": "Mdef", "node": {".class": "Var", "flags": [], "fullname": "liquid.environment.Environment.strict_filters", "name": "strict_filters", "type": "builtins.bool"}}, "strip_tags": {".class": "SymbolTableNode", "implicit": true, "kind": "Mdef", "node": {".class": "Var", "flags": [], "fullname": "liquid.environment.Environment.strip_tags", "name": "strip_tags", "type": "builtins.bool"}}, "tag_end_string": {".class": "SymbolTableNode", "implicit": true, "kind": "Mdef", "node": {".class": "Var", "flags": [], "fullname": "liquid.environment.Environment.tag_end_string", "name": "tag_end_string", "type": "builtins.str"}}, "tag_start_string": {".class": "SymbolTableNode", "implicit": true, "kind": "Mdef", "node": {".class": "Var", "flags": [], "fullname": "liquid.environment.Environment.tag_start_string", "name": "tag_start_string", "type": "builtins.str"}}, "tags": {".class": "SymbolTableNode", "implicit": true, "kind": "Mdef", "node": {".class": "Var", "flags": ["explicit_self_type", "is_ready"], "fullname": "liquid.environment.Environment.tags", "name": "tags", "type": {".class": "Instance", "args": ["builtins.str", "liquid.tag.Tag"], "type_ref": "builtins.dict"}}}, "template_class": {".class": "SymbolTableNode", "kind": "Mdef", "node": {".class": "Var", "flags": ["is_initialized_in_class", "has_explicit_value"], "fullname": "liquid.environment.Environment.template_class", "name": "template_class", "type": {".class": "CallableType", "arg_kinds": [0, 0, 1, 1, 1, 1, 1], "arg_names": ["env", "parse_tree", "name", "path", "globals", "matter", "uptodate"], "arg_types": ["liquid.environment.Environment", "liquid.ast.ParseTree", "builtins.str", {".class": "UnionType", "items": ["builtins.str", "pathlib.Path", {".class": "NoneType"}]}, {".class": "UnionType", "items": [{".class": "Instance", "args": ["builtins.str", "builtins.object"], "type_ref": "builtins.dict"}, {".class": "NoneType"}]}, {".class": "UnionType", "items": [{".class": "Instance", "args": ["builtins.str", "builtins.object"], "type_ref": "typing.Mapping"}, {".class": "NoneType"}]}, {".class": "UnionType", "items": [{".class": "CallableType", "arg_kinds": [], "arg_names": [], "arg_types": [], "bound_args": [], "def_extras": {}, "fallback": "builtins.function", "from_concatenate": false, "implicit": false, "is_ellipsis_args": false, "name": null, "ret_type": "builtins.bool", "type_guard": null, "variables": []}, {".class": "CallableType", "arg_kinds": [], "arg_names": [], "arg_types": [], "bound_args": [], "def_extras": {}, "fallback": "builtins.function", "from_concatenate": false, "implicit": false, "is_ellipsis_args": false, "name": null, "ret_type": {".class": "Instance", "args": ["builtins.bool"], "type_ref": "typing.Awaitable"}, "type_guard": null, "variables": []}, {".class": "NoneType"}]}], "bound_args": ["liquid.template.BoundTemplate"], "def_extras": {"first_arg": "self"}, "fallback": "builtins.type", "from_concatenate": false, "implicit": false, "is_ellipsis_args": false, "name": null, "ret_type": "liquid.template.BoundTemplate", "type_guard": null, "variables": []}}}, "template_comments": {".class": "SymbolTableNode", "implicit": true, "kind": "Mdef", "node": {".class": "Var", "flags": [], "fullname": "liquid.environment.Environment.template_comments", "name": "template_comments", "type": "builtins.bool"}}, "undefined": {".class": "SymbolTableNode", "implicit": true, "kind": "Mdef", "node": {".class": "Var", "flags": [], "fullname": "liquid.environment.Environment.undefined", "name": "undefined", "type": {".class": "TypeType", "item": "liquid.context.Undefined"}}}}, "slots": null, "tuple_type": null, "type_vars": [], "typeddict_type": null}}, "Error": {".class": "SymbolTableNode", "cross_ref": "liquid.exceptions.Error", "kind": "Gdef"}, "FilteredExpression": {".class": "SymbolTableNode", "cross_ref": "liquid.expression.FilteredExpression", "kind": "Gdef"}, "LRUCache": {".class": "SymbolTableNode", "cross_ref": "liquid.utils.cache.LRUCache", "kind": "Gdef"}, "LiquidSyntaxError": {".class": "SymbolTableNode", "cross_ref": "liquid.exceptions.LiquidSyntaxError", "kind": "Gdef"}, "LoopExpression": {".class": "SymbolTableNode", "cross_ref": "liquid.expression.LoopExpression", "kind": "Gdef"}, "Mapping": {".class": "SymbolTableNode", "cross_ref": "typing.Mapping", "kind": "Gdef"}, "Mode": {".class": "SymbolTableNode", "cross_ref": "liquid.mode.Mode", "kind": "Gdef"}, "MutableMapping": {".class": "SymbolTableNode", "cross_ref": "typing.MutableMapping", "kind": "Gdef"}, "Optional": {".class": "SymbolTableNode", "cross_ref": "typing.Optional", "kind": "Gdef"}, "Path": {".class": "SymbolTableNode", "cross_ref": "pathlib.Path", "kind": "Gdef"}, "TYPE_CHECKING": {".class": "SymbolTableNode", "cross_ref": "typing.TYPE_CHECKING", "kind": "Gdef"}, "Tag": {".class": "SymbolTableNode", "cross_ref": "liquid.tag.Tag", "kind": "Gdef"}, "Template": {".class": "SymbolTableNode", "kind": "Gdef", "node": {".class": "FuncDef", "arg_kinds": [0, 1, 1, 1, 1, 1, 1, 1, 1, 1, 1, 1, 1, 1, 1, 1, 1], "arg_names": ["source", "tag_start_string", "tag_end_string", "statement_start_string", "statement_end_string", "strip_tags", "tolerance", "undefined", "strict_filters", "autoescape", "auto_reload", "cache_size", "globals", "template_comments", "comment_start_string", "comment_end_string", "expression_cache_size"], "flags": [], "fullname": "liquid.environment.Template", "name": "Template", "type": {".class": "CallableType", "arg_kinds": [0, 1, 1, 1, 1, 1, 1, 1, 1, 1, 1, 1, 1, 1, 1, 1, 1], "arg_names": ["source", "tag_start_string", "tag_end_string", "statement_start_string", "statement_end_string", "strip_tags", "tolerance", "undefined", "strict_filters", "autoescape", "auto_reload", "cache_size", "globals", "template_comments", "comment_start_string", "comment_end_string", "expression_cache_size"], "arg_types": ["builtins.str", "builtins.str", "builtins.str", "builtins.str", "builtins.str", "builtins.bool", "liquid.mode.Mode", {".class": "TypeType", "item": "liquid.context.Undefined"}, "builtins.bool", "builtins.bool", "builtins.bool", "builtins.int", {".class": "UnionType", "items": [{".class": "Instance", "args": ["builtins.str", "builtins.object"], "type_ref": "typing.Mapping"}, {".class": "NoneType"}]}, "builtins.bool", "builtins.str", "builtins.str", "builtins.int"], "bound_args": [], "def_extras": {"first_arg": null}, "fallback": "builtins.function", "from_concatenate": false, "implicit": false, "is_ellipsis_args": false, "name": "Template", "ret_type": "liquid.template.BoundTemplate", "type_guard": null, "variables": []}}}, "TokenStream": {".class": "SymbolTableNode", "cross_ref": "liquid.stream.TokenStream", "kind": "Gdef"}, "Tuple": {".class": "SymbolTableNode", "cross_ref": "typing.Tuple", "kind": "Gdef"}, "Type": {".class": "SymbolTableNode", "cross_ref": "typing.Type", "kind": "Gdef"}, "Undefined": {".class": "SymbolTableNode", "cross_ref": "liquid.context.Undefined", "kind": "Gdef"}, "Union": {".class": "SymbolTableNode", "cross_ref": "typing.Union", "kind": "Gdef"}, "__annotations__": {".class": "SymbolTableNode", "kind": "Gdef", "node": {".class": "Var", "flags": ["is_ready"], "fullname": "liquid.environment.__annotations__", "name": "__annotations__", "type": {".class": "Instance", "args": ["builtins.str", {".class": "AnyType", "missing_import_name": null, "source_any": null, "type_of_any": 6}], "type_ref": "builtins.dict"}}}, "__doc__": {".class": "SymbolTableNode", "kind": "Gdef", "node": {".class": "Var", "flags": ["is_ready"], "fullname": "liquid.environment.__doc__", "name": "__doc__", "type": "builtins.str"}}, "__file__": {".class": "SymbolTableNode", "kind": "Gdef", "node": {".class": "Var", "flags": ["is_ready"], "fullname": "liquid.environment.__file__", "name": "__file__", "type": "builtins.str"}}, "__name__": {".class": "SymbolTableNode", "kind": "Gdef", "node": {".class": "Var", "flags": ["is_ready"], "fullname": "liquid.environment.__name__", "name": "__name__", "type": "builtins.str"}}, "__package__": {".class": "SymbolTableNode", "kind": "Gdef", "node": {".class": "Var", "flags": ["is_ready"], "fullname": "liquid.environment.__package__", "name": "__package__", "type": "builtins.str"}}, "annotations": {".class": "SymbolTableNode", "cross_ref": "__future__.annotations", "kind": "Gdef"}, "ast": {".class": "SymbolTableNode", "cross_ref": "liquid.ast", "kind": "Gdef"}, "builtin": {".class": "SymbolTableNode", "cross_ref": "liquid.builtin", "kind": "Gdef"}, "get_implicit_environment": {".class": "SymbolTableNode", "kind": "Gdef", "node": {".class": "Decorator", "func": {".class": "FuncDef", "arg_kinds": [0, 0, 0, 0, 0, 0, 0, 0, 0, 0, 0, 0, 0, 0, 0, 0, 0], "arg_names": ["tag_start_string", "tag_end_string", "statement_start_string", "statement_end_string", "strip_tags", "tolerance", "loader", "undefined", "strict_filters", "autoescape", "auto_reload", "cache_size", "globals", "template_comments", "comment_start_string", "comment_end_string", "expression_cache_size"], "flags": ["is_decorated"], "fullname": "liquid.environment.get_implicit_environment", "name": "get_implicit_environment", "type": {".class": "CallableType", "arg_kinds": [0, 0, 0, 0, 0, 0, 0, 0, 0, 0, 0, 0, 0, 0, 0, 0, 0], "arg_names": ["tag_start_string", "tag_end_string", "statement_start_string", "statement_end_string", "strip_tags", "tolerance", "loader", "undefined", "strict_filters", "autoescape", "auto_reload", "cache_size", "globals", "template_comments", "comment_start_string", "comment_end_string", "expression_cache_size"], "arg_types": ["builtins.str", "builtins.str", "builtins.str", "builtins.str", "builtins.bool", "liquid.mode.Mode", {".class": "UnionType", "items": ["liquid.loaders.BaseLoader", {".class": "NoneType"}]}, {".class": "TypeType", "item": "liquid.context.Undefined"}, "builtins.bool", "builtins.bool", "builtins.bool", "builtins.int", {".class": "UnionType", "items": [{".class": "Instance", "args": ["builtins.str", "builtins.object"], "type_ref": "typing.Mapping"}, {".class": "NoneType"}]}, "builtins.bool", "builtins.str", "builtins.str", "builtins.int"], "bound_args": [], "def_extras": {"first_arg": null}, "fallback": "builtins.function", "from_concatenate": false, "implicit": false, "is_ellipsis_args": false, "name": "get_implicit_environment", "ret_type": "liquid.environment.Environment", "type_guard": null, "variables": []}}, "is_overload": false, "var": {".class": "Var", "flags": ["is_ready"], "fullname": null, "name": "get_implicit_environment", "type": {".class": "Instance", "args": ["liquid.environment.Environment"], "type_ref": "functools._lru_cache_wrapper"}}}}, "get_lexer": {".class": "SymbolTableNode", "cross_ref": "liquid.lex.get_lexer", "kind": "Gdef"}, "get_parser": {".class": "SymbolTableNode", "cross_ref": "liquid.parse.get_parser", "kind": "Gdef"}, "loaders": {".class": "SymbolTableNode", "cross_ref": "liquid.loaders", "kind": "Gdef"}, "lookup_warning": {".class": "SymbolTableNode", "cross_ref": "liquid.exceptions.lookup_warning", "kind": "Gdef"}, "lru_cache": {".class": "SymbolTableNode", "cross_ref": "functools.lru_cache", "kind": "Gdef"}, "parse_boolean_expression": {".class": "SymbolTableNode", "cross_ref": "liquid.expressions.boolean.parse.parse", "kind": "Gdef"}, "parse_filtered_expression": {".class": "SymbolTableNode", "cross_ref": "liquid.expressions.filtered.parse.parse", "kind": "Gdef"}, "parse_loop_expression": {".class": "SymbolTableNode", "cross_ref": "liquid.expressions.loop.parse.parse", "kind": "Gdef"}, "warnings": {".class": "SymbolTableNode", "cross_ref": "warnings", "kind": "Gdef"}}, "path": "/home/james/projects/liquid/liquid/environment.py"}