{"id": "re", "path": "/home/james/.local/share/virtualenvs/python_liquid_babel-50H9tmte/lib/python3.10/site-packages/mypy/typeshed/stdlib/re.pyi", "mtime": 1662632511, "size": 5091, "hash": "9ede424d30a9021a8299f8868cc0d066af74aeb252a46373549a5378cc5a0fce", "data_mtime": 1662447232, "dependencies": ["enum", "sre_compile", "sys", "_typeshed", "collections.abc", "sre_constants", "typing", "typing_extensions", "builtins", "abc", "array", "ctypes", "mmap", "pickle"], "suppressed": [], "options": {"warn_unreachable": false, "local_partial_types": false, "always_true": [], "disallow_any_generics": false, "ignore_errors": false, "warn_return_any": false, "strict_optional": true, "allow_redefinition": false, "follow_imports": "silent", "ignore_missing_imports": true, "disallow_subclassing_any": false, "mypyc": false, "strict_optional_whitelist": null, "disallow_incomplete_defs": false, "bazel": false, "show_none_errors": true, "warn_no_return": true, "disallow_untyped_defs": false, "always_false": [], "allow_untyped_globals": false, "strict_equality": false, "disallow_any_expr": false, "follow_imports_for_stubs": false, "warn_unused_ignores": false, "check_untyped_defs": false, "disallow_any_explicit": false, "disallow_any_unimported": false, "platform": "linux", "plugins": [], "disallow_untyped_decorators": false, "disallow_any_decorated": false, "implicit_reexport": true, "no_implicit_optional": false, "disallow_untyped_calls": false, "strict_concatenate": false}, "dep_prios": [10, 10, 10, 5, 5, 5, 5, 5, 5, 30, 30, 30, 30, 30], "dep_lines": [1, 2, 3, 4, 5, 6, 7, 8, 1, 1, 1, 1, 1, 1], "interface_hash": "c515ac7431f18bed8537fa74de10c3964ae056fa7f89a55b92e43d326450f92b", "version_id": "0.971", "ignore_all": true, "plugin_data": null}